{
  "id": "dadc4d8959ad684715c169ee61886ce0",
  "name": "latest",
  "title": "latest",
  "description": "Category: Youtube Channel Art,Fashion & Style | Tags: club,new",
  "data": {
    "background": {
      "type": "solid",
      "color": "#ffefbe"
    },
    "gridSettings": {
      "gridSize": 20,
      "showGrid": false,
      "snapToGrid": true,
      "snapToObjects": true,
      "snapTolerance": 5
    },
    "backgroundColor": "#ffefbe",
    "viewportSettings": {
      "panX": 0,
      "panY": 0,
      "zoom": 1
    }
  },
  "layers": [
    {
      "id": 1073870016661241300,
      "name": "Layer 1",
      "type": "shape",
      "locked": false,
      "zIndex": 9,
      "plugins": {},
      "visible": true,
      "transform": {
        "x": 422,
        "y": 692,
        "skewX": 0,
        "skewY": 0,
        "width": 108,
        "height": 8,
        "scaleX": 1,
        "scaleY": 1,
        "opacity": 1,
        "rotation": -90.00000000000037
      },
      "properties": {
        "x1": 0,
        "x2": 100,
        "y1": 0,
        "y2": 100,
        "fill": {
          "type": "solid",
          "color": "#000000",
          "opacity": 1
        },
        "sides": 4,
        "points": 5,
        "stroke": "#000000",
        "shapeType": "rectangle",
        "innerRadius": 0.5,
        "strokeWidth": 0,
        "cornerRadius": 0,
        "strokeOpacity": 1
      }
    },
    {
      "id": 1061990016661241300,
      "name": "Layer 2",
      "type": "shape",
      "locked": false,
      "zIndex": 8,
      "plugins": {},
      "visible": true,
      "transform": {
        "x": 28,
        "y": 692,
        "skewX": 0,
        "skewY": 0,
        "width": 108,
        "height": 8,
        "scaleX": 1,
        "scaleY": 1,
        "opacity": 1,
        "rotation": -90.00000000000037
      },
      "properties": {
        "x1": 0,
        "x2": 100,
        "y1": 0,
        "y2": 100,
        "fill": {
          "type": "solid",
          "color": "#000000",
          "opacity": 1
        },
        "sides": 4,
        "points": 5,
        "stroke": "#000000",
        "shapeType": "rectangle",
        "innerRadius": 0.5,
        "strokeWidth": 0,
        "cornerRadius": 0,
        "strokeOpacity": 1
      }
    },
    {
      "id": 1052130016661241300,
      "name": "Layer 3",
      "type": "shape",
      "locked": false,
      "zIndex": 7,
      "plugins": {},
      "visible": true,
      "transform": {
        "x": 78,
        "y": 742,
        "skewX": 0,
        "skewY": 0,
        "width": 402,
        "height": 8,
        "scaleX": 1,
        "scaleY": 1,
        "opacity": 1,
        "rotation": 0
      },
      "properties": {
        "x1": 0,
        "x2": 100,
        "y1": 0,
        "y2": 100,
        "fill": {
          "type": "solid",
          "color": "#000000",
          "opacity": 1
        },
        "sides": 4,
        "points": 5,
        "stroke": "#000000",
        "shapeType": "rectangle",
        "innerRadius": 0.5,
        "strokeWidth": 0,
        "cornerRadius": 0,
        "strokeOpacity": 1
      }
    },
    {
      "id": 1041810016661241300,
      "name": "Layer 4",
      "type": "shape",
      "locked": false,
      "zIndex": 6,
      "plugins": {},
      "visible": true,
      "transform": {
        "x": 78,
        "y": 642,
        "skewX": 0,
        "skewY": 0,
        "width": 402,
        "height": 8,
        "scaleX": 1,
        "scaleY": 1,
        "opacity": 1,
        "rotation": 0
      },
      "properties": {
        "x1": 0,
        "x2": 100,
        "y1": 0,
        "y2": 100,
        "fill": {
          "type": "solid",
          "color": "#000000",
          "opacity": 1
        },
        "sides": 4,
        "points": 5,
        "stroke": "#000000",
        "shapeType": "rectangle",
        "innerRadius": 0.5,
        "strokeWidth": 0,
        "cornerRadius": 0,
        "strokeOpacity": 1
      }
    },
    {
      "id": 1021200016661241300,
      "name": "BY HALEY WU",
      "type": "text",
      "locked": false,
      "zIndex": 5,
      "plugins": {},
      "visible": true,
      "transform": {
        "x": 138,
        "y": 688,
        "skewX": 0,
        "skewY": 0,
        "width": 282,
        "height": 52,
        "scaleX": 1,
        "scaleY": 1,
        "opacity": 1,
        "rotation": 0
      },
      "properties": {
        "text": "BY HALEY WU",
        "color": "#000000",
        "fontSize": "45",
        "fontStyle": "normal",
        "textAlign": "left",
        "autoResize": {
          "mode": "both",
          "enabled": true,
          "padding": {
            "top": 0,
            "left": 0,
            "right": 0,
            "bottom": 0
          }
        },
        "fontFamily": "comfortaa",
        "fontWeight": "normal",
        "lineHeight": 1.2,
        "letterSpacing": 0,
        "textDecoration": "none"
      }
    },
    {
      "id": 5422790016661241000,
      "name": "staycay beach looks",
      "type": "text",
      "locked": false,
      "zIndex": 4,
      "plugins": {},
      "visible": true,
      "transform": {
        "x": 78,
        "y": 282,
        "skewX": 0,
        "skewY": 0,
        "width": 630,
        "height": 331,
        "scaleX": 1,
        "scaleY": 1,
        "opacity": 1,
        "rotation": 0
      },
      "properties": {
        "text": "staycay beach looks",
        "color": "#000000",
        "fontSize": 194.63567394923152,
        "fontStyle": "normal",
        "textAlign": "left",
        "autoResize": {
          "mode": "both",
          "enabled": true,
          "padding": {
            "top": 0,
            "left": 0,
            "right": 0,
            "bottom": 0
          }
        },
        "fontFamily": "playball",
        "fontWeight": "normal",
        "lineHeight": 1.2,
        "letterSpacing": 0,
        "textDecoration": "none"
      }
    },
    {
      "id": 75990016661241310,
      "name": "Layer 7",
      "type": "image",
      "locked": false,
      "zIndex": 3,
      "plugins": {},
      "visible": true,
      "transform": {
        "x": 552,
        "y": 0,
        "skewX": 0,
        "skewY": 0,
        "width": 880,
        "height": 1320,
        "scaleX": 1,
        "scaleY": 1,
        "opacity": 1,
        "rotation": 0
      },
      "properties": {
        "alt": "Layer 7",
        "hue": 0,
        "src": "/cache/media_cache/images_unsplash_com_L2ZsYWdnZWQvcGhvdG8tMTU3MDcwMDAwNTg4MC00ZWNkYjg1OTVkNGE=.jpg",
        "blur": 0,
        "flipX": false,
        "flipY": false,
        "sepia": 0,
        "invert": 0,
        "shadow": {
          "enabled": false
        },
        "quality": 80,
        "contrast": 1,
        "grayscale": 0,
        "scaleMode": "fill",
        "brightness": 1,
        "saturation": 1,
        "objectPosition": "center",
        "preserveAspectRatio": true
      }
    },
    {
      "id": 4830350016661241000,
      "name": "Layer 8",
      "type": "image",
      "locked": false,
      "zIndex": 2,
      "plugins": {},
      "visible": true,
      "transform": {
        "x": 1202,
        "y": 0,
        "skewX": 0,
        "skewY": 0,
        "width": 720,
        "height": 1080,
        "scaleX": 1,
        "scaleY": 1,
        "opacity": 1,
        "rotation": 0
      },
      "properties": {
        "alt": "Layer 8",
        "hue": 0,
        "src": "/cache/media_cache/images_unsplash_com_L3Bob3RvLTE1MTQzMTUzODQ3NjMtYmE0MDE3Nzk0MTBm.jpg",
        "blur": 0,
        "flipX": false,
        "flipY": false,
        "sepia": 0,
        "invert": 0,
        "shadow": {
          "enabled": false
        },
        "quality": 80,
        "contrast": 1,
        "grayscale": 0,
        "scaleMode": "fill",
        "brightness": 1,
        "saturation": 1,
        "objectPosition": "center",
        "preserveAspectRatio": true
      }
    },
    {
      "id": 4847960016661241000,
      "name": "Layer 9",
      "type": "shape",
      "locked": false,
      "zIndex": 1,
      "plugins": {},
      "visible": true,
      "transform": {
        "x": 532,
        "y": 0,
        "skewX": 0,
        "skewY": 0,
        "width": 1319,
        "height": 1080,
        "scaleX": 1,
        "scaleY": 1,
        "opacity": 1,
        "rotation": 0
      },
      "properties": {
        "x1": 0,
        "x2": 100,
        "y1": 0,
        "y2": 100,
        "fill": {
          "type": "solid",
          "color": "#ffffff",
          "opacity": 1
        },
        "sides": 4,
        "points": 5,
        "stroke": "#000000",
        "shapeType": "rectangle",
        "innerRadius": 0.5,
        "strokeWidth": 0,
        "cornerRadius": 0,
        "strokeOpacity": 1
      }
    }
  ],
  "thumbnail": "/cache/tpl/previews/dadc4d8959ad684715c169ee61886ce0.jpg",
  "width": 2560,
  "height": 1440,
  "userId": "legacy_import",
  "projectId": null,
  "isPublic": true,
  "createdAt": "2023-06-10T12:24:12.000Z",
  "updatedAt": "2023-06-10T12:24:12.000Z",
  "originalId": 871
}